rongjilv.py
calculate_maxi_min-1.3.dist-info/METADATA
calculate_maxi_min-1.3.dist-info/WHEEL
calculate_maxi_min-1.3.dist-info/top_level.txt
calculate_maxi_min-1.3.dist-info/RECORD
