Metadata-Version: 2.1
Name: calculate-maxi-min
Version: 1.3
Summary: 计算最大最小值
Home-page: https://gitee.com/jia_kai_peng/calcalute
Author: jkp
Author-email: 1543889217@qq.com
License: UNKNOWN
Platform: UNKNOWN
Classifier: Programming Language :: Python :: 3
Classifier: License :: OSI Approved :: MIT License
Classifier: Operating System :: OS Independent
Requires: loguru
Requires: pandas
